vtds_core/__init__.py
vtds_core/base_config.py
vtds_core/runner.py
vtds_core/wrapper.py
vtds_core/private/__init__.py
vtds_core/private/base_config.py
vtds_core/private/common.py
vtds_core/private/config.py
vtds_core/private/deploy.py
vtds_core/private/git_config.py
vtds_core/private/git_modules.py
vtds_core/private/git_repo.py
vtds_core/private/remove.py
vtds_core/private/sample_request.py
vtds_core/private/show_config.py
vtds_core/private/url_config.py
vtds_core/private/validate.py
vtds_core/private/config/README.md
vtds_core/private/config/config.yaml
vtds_core/private/config/test_overlay.yaml
vtds_core-0.0.15.dist-info/licenses/LICENSE
vtds_core-0.0.15.dist-info/METADATA
vtds_core-0.0.15.dist-info/WHEEL
vtds_core-0.0.15.dist-info/entry_points.txt
vtds_core-0.0.15.dist-info/top_level.txt
vtds_core-0.0.15.dist-info/RECORD
